nonebot_plugin_nsfw-0.13.dist-info/METADATA
nonebot_plugin_nsfw-0.13.dist-info/WHEEL
nonebot_plugin_nsfw-0.13.dist-info/entry_points.txt
nonebot_plugin_nsfw-0.13.dist-info/licenses/LICENSE
nonebot_plugin_nsfw/__init__.py
nonebot_plugin_nsfw/config.py
nonebot_plugin_nsfw/deps.py
nonebot_plugin_nsfw/loader.py
nonebot_plugin_nsfw/vendor_nsfw_model.py
nonebot_plugin_nsfw-0.13.dist-info/RECORD
