Metadata-Version: 2.1
Name: nonebot-plugin-nsfw
Version: 0.13
Summary: 群聊 NSFW 图片检测插件，带有撤回、警告、禁言等功能。使用 Safety Checker / NSFW Model。
Author-Email: iyume <iyumelive@gmail.com>
License: Apache-2.0
Requires-Python: >=3.9
Requires-Dist: nonebot2>=2.0
Requires-Dist: nonebot-adapter-onebot>=2.0
Requires-Dist: Pillow>=8.4.0
Requires-Dist: httpx
Provides-Extra: safety-checker
Requires-Dist: safety-checker[sdhook]>=0.5; extra == "safety-checker"
Requires-Dist: numpy; extra == "safety-checker"
Provides-Extra: nsfw-model
Requires-Dist: tensorflow>=2.2.0; extra == "nsfw-model"
Requires-Dist: tensorflow-hub>=0.12; extra == "nsfw-model"
Requires-Dist: numpy; extra == "nsfw-model"
Provides-Extra: nsfw-image-detection
Requires-Dist: transformers==4.*; extra == "nsfw-image-detection"
